{
  "items": [
    {
      "kind": "youtube#searchResult",
      "etag": "y7NPEPUHnrx9lvfq8UhGqapp0Go",
      "id": {
        "kind": "youtube#video",
        "videoId": "tNu7-GpAwfg"
      },
      "snippet": {
        "publishedAt": "2021-05-10T20:41:52Z",
        "channelId": "UClVf_Gfo8oouXAWQ3TghG2Q",
        "title": "Aladdin Full Movie [HD] | Animation Disney Movies",
        "description": "aladdin #fullmovie #disneymovies #newmovies #oldmovies #animationmovies new animated movies 2020,New animated movies ...",
        "thumbnails": {
          "default": {
            "url": "https://i.ytimg.com/vi/tNu7-GpAwfg/default.jpg",
            "width": 120,
            "height": 90
          },
          "medium": {
            "url": "https://i.ytimg.com/vi/tNu7-GpAwfg/mqdefault.jpg",
            "width": 320,
            "height": 180
          },
          "high": {
            "url": "https://i.ytimg.com/vi/tNu7-GpAwfg/hqdefault.jpg",
            "width": 480,
            "height": 360
          }
        },
        "channelTitle": "ANIME TOONS TV ®",
        "liveBroadcastContent": "none",
        "publishTime": "2021-05-10T20:41:52Z"
      }
    },
    {
      "kind": "youtube#searchResult",
      "etag": "lcm9GmuhQ8vEezkt1Droxtm2tw8",
      "id": {
        "kind": "youtube#video",
        "videoId": "0kHOYavm7VY"
      },
      "snippet": {
        "publishedAt": "2020-07-10T18:40:06Z",
        "channelId": "UCe9FHiqr86WggS_gaPGMfMw",
        "title": "Snow White and the Seven Dwarfs 1937 Full Movie",
        "description": "Snow White and the Seven Dwarfs is a 1937 American animated musical fantasy film produced by Walt Disney Productions and ...",
        "thumbnails": {
          "default": {
            "url": "https://i.ytimg.com/vi/0kHOYavm7VY/default.jpg",
            "width": 120,
            "height": 90
          },
          "medium": {
            "url": "https://i.ytimg.com/vi/0kHOYavm7VY/mqdefault.jpg",
            "width": 320,
            "height": 180
          },
          "high": {
            "url": "https://i.ytimg.com/vi/0kHOYavm7VY/hqdefault.jpg",
            "width": 480,
            "height": 360
          }
        },
        "channelTitle": "ThePopDiva93 3.0",
        "liveBroadcastContent": "none",
        "publishTime": "2020-07-10T18:40:06Z"
      }
    },
    {
      "kind": "youtube#searchResult",
      "etag": "nE2n4TX6XGMHt_l86kj5mDlHlYA",
      "id": {
        "kind": "youtube#video",
        "videoId": "-Vui-DhwIAg"
      },
      "snippet": {
        "publishedAt": "2022-08-01T16:01:22Z",
        "channelId": "UC_IRYSp4auq7hKLvziWVH6w",
        "title": "Cars on the Road | Official Trailer | Disney+",
        "description": "Lightning and Mater are back! Watch the trailer for Disney and Pixar's Cars on the Road and start streaming the Original series, ...",
        "thumbnails": {
          "default": {
            "url": "https://i.ytimg.com/vi/-Vui-DhwIAg/default.jpg",
            "width": 120,
            "height": 90
          },
          "medium": {
            "url": "https://i.ytimg.com/vi/-Vui-DhwIAg/mqdefault.jpg",
            "width": 320,
            "height": 180
          },
          "high": {
            "url": "https://i.ytimg.com/vi/-Vui-DhwIAg/hqdefault.jpg",
            "width": 480,
            "height": 360
          }
        },
        "channelTitle": "Pixar",
        "liveBroadcastContent": "none",
        "publishTime": "2022-08-01T16:01:22Z"
      }
    },
    {
      "kind": "youtube#searchResult",
      "etag": "HBXy4tq1ImLnWw_6YhJcOycKlJE",
      "id": {
        "kind": "youtube#video",
        "videoId": "c5tzU4MGCNs"
      },
      "snippet": {
        "publishedAt": "2022-05-12T22:47:38Z",
        "channelId": "UCNcdbMyA59zE-Vk668bKWOg",
        "title": "🔴 LIVE! All of Minnie&#39;s Bow-Toons! 🎀  | @Disney Junior",
        "description": "There's no business like bow business! Minnie Mouse teams up with her friend Daisy Duck to open up Minnie's Bow-tique, a store ...",
        "thumbnails": {
          "default": {
            "url": "https://i.ytimg.com/vi/c5tzU4MGCNs/default_live.jpg",
            "width": 120,
            "height": 90
          },
          "medium": {
            "url": "https://i.ytimg.com/vi/c5tzU4MGCNs/mqdefault_live.jpg",
            "width": 320,
            "height": 180
          },
          "high": {
            "url": "https://i.ytimg.com/vi/c5tzU4MGCNs/hqdefault_live.jpg",
            "width": 480,
            "height": 360
          }
        },
        "channelTitle": "Disney Junior",
        "liveBroadcastContent": "live",
        "publishTime": "2022-05-12T22:47:38Z"
      }
    },
    {
      "kind": "youtube#searchResult",
      "etag": "Y1Ut28TQ24kl7tCX-fYfi6Qgcyo",
      "id": {
        "kind": "youtube#video",
        "videoId": "TEt7rkD4h70"
      },
      "snippet": {
        "publishedAt": "2022-02-06T15:00:23Z",
        "channelId": "UC69ircTslibVSTzQVfYluBQ",
        "title": "Top 10 Disney Movies of 2021",
        "description": "If you want to know the best movies produced by Disney including Marvel & 20th Century Studios you should definitely watch our ...",
        "thumbnails": {
          "default": {
            "url": "https://i.ytimg.com/vi/TEt7rkD4h70/default.jpg",
            "width": 120,
            "height": 90
          },
          "medium": {
            "url": "https://i.ytimg.com/vi/TEt7rkD4h70/mqdefault.jpg",
            "width": 320,
            "height": 180
          },
          "high": {
            "url": "https://i.ytimg.com/vi/TEt7rkD4h70/hqdefault.jpg",
            "width": 480,
            "height": 360
          }
        },
        "channelTitle": "communiTV",
        "liveBroadcastContent": "none",
        "publishTime": "2022-02-06T15:00:23Z"
      }
    },
    {
      "kind": "youtube#searchResult",
      "etag": "t8Bu13P9sVM2noB3Kunzyz2jWQE",
      "id": {
        "kind": "youtube#video",
        "videoId": "zDavCpNq_58"
      },
      "snippet": {
        "publishedAt": "2021-07-05T05:57:11Z",
        "channelId": "UCUtDKL4KLw4t31XmASFAiSg",
        "title": "BarbieAs The Island Princess 2007 Full Movie   Barbie Official Movies",
        "description": "Thank you for watching this video! Please subscribe to see more from me, give this video a thumbs up if you enjoyed and ...",
        "thumbnails": {
          "default": {
            "url": "https://i.ytimg.com/vi/zDavCpNq_58/default.jpg",
            "width": 120,
            "height": 90
          },
          "medium": {
            "url": "https://i.ytimg.com/vi/zDavCpNq_58/mqdefault.jpg",
            "width": 320,
            "height": 180
          },
          "high": {
            "url": "https://i.ytimg.com/vi/zDavCpNq_58/hqdefault.jpg",
            "width": 480,
            "height": 360
          }
        },
        "channelTitle": "Disney MOVIES",
        "liveBroadcastContent": "none",
        "publishTime": "2021-07-05T05:57:11Z"
      }
    },
    {
      "kind": "youtube#searchResult",
      "etag": "lqFvloU_0cxKioBj7ZWJuJTGn9Y",
      "id": {
        "kind": "youtube#video",
        "videoId": "LCESRrQl3VY"
      },
      "snippet": {
        "publishedAt": "2022-06-03T02:14:23Z",
        "channelId": "UCWnvjBGmorQeXqp1lPiFtOA",
        "title": "Moana full movie 2016 in english animation movie kids new Disney cartoon",
        "description": "Moana full movie 2016 in english animation Moana,moana Movie,disney We've got more Cool stuff for you! SUBSCRIBE ...",
        "thumbnails": {
          "default": {
            "url": "https://i.ytimg.com/vi/LCESRrQl3VY/default.jpg",
            "width": 120,
            "height": 90
          },
          "medium": {
            "url": "https://i.ytimg.com/vi/LCESRrQl3VY/mqdefault.jpg",
            "width": 320,
            "height": 180
          },
          "high": {
            "url": "https://i.ytimg.com/vi/LCESRrQl3VY/hqdefault.jpg",
            "width": 480,
            "height": 360
          }
        },
        "channelTitle": "Viver TV Cartoon",
        "liveBroadcastContent": "none",
        "publishTime": "2022-06-03T02:14:23Z"
      }
    },
    {
      "kind": "youtube#searchResult",
      "etag": "uhn7AZiRrodXUBsROS2tPFt6wPg",
      "id": {
        "kind": "youtube#video",
        "videoId": "SzO7oCMWJL8"
      },
      "snippet": {
        "publishedAt": "2019-01-04T08:51:59Z",
        "channelId": "UCwJK1RFbprEIzdClxTNLmSw",
        "title": "New Animation Movies 2019 Full Movies English - Kids movies - Comedy Movies - Cartoon Disney",
        "description": "New Animation Movies 2019 Full Movies English - Kids movies - Comedy Movies - Cartoon Disney.",
        "thumbnails": {
          "default": {
            "url": "https://i.ytimg.com/vi/SzO7oCMWJL8/default.jpg",
            "width": 120,
            "height": 90
          },
          "medium": {
            "url": "https://i.ytimg.com/vi/SzO7oCMWJL8/mqdefault.jpg",
            "width": 320,
            "height": 180
          },
          "high": {
            "url": "https://i.ytimg.com/vi/SzO7oCMWJL8/hqdefault.jpg",
            "width": 480,
            "height": 360
          }
        },
        "channelTitle": "Joe Bauer",
        "liveBroadcastContent": "none",
        "publishTime": "2019-01-04T08:51:59Z"
      }
    },
    {
      "kind": "youtube#searchResult",
      "etag": "QfVmGHs1DDxUmVoeZU1dvwo6uPk",
      "id": {
        "kind": "youtube#video",
        "videoId": "cKOegEuCcfw"
      },
      "snippet": {
        "publishedAt": "2022-08-01T12:27:16Z",
        "channelId": "UCZGYJFUizSax-yElQaFDp5Q",
        "title": "Andor | Official Trailer | Disney+",
        "description": "Watch the new trailer for #Andor, a Star Wars original series, streaming only on Disney+. Experience the three-episode premiere ...",
        "thumbnails": {
          "default": {
            "url": "https://i.ytimg.com/vi/cKOegEuCcfw/default.jpg",
            "width": 120,
            "height": 90
          },
          "medium": {
            "url": "https://i.ytimg.com/vi/cKOegEuCcfw/mqdefault.jpg",
            "width": 320,
            "height": 180
          },
          "high": {
            "url": "https://i.ytimg.com/vi/cKOegEuCcfw/hqdefault.jpg",
            "width": 480,
            "height": 360
          }
        },
        "channelTitle": "Star Wars",
        "liveBroadcastContent": "none",
        "publishTime": "2022-08-01T12:27:16Z"
      }
    },
    {
      "kind": "youtube#searchResult",
      "etag": "ICHn5tjzSta0zHRUlqFkdrmZFAg",
      "id": {
        "kind": "youtube#video",
        "videoId": "9qPKlNoGzyg"
      },
      "snippet": {
        "publishedAt": "2022-06-26T15:53:39Z",
        "channelId": "UCSYhnhdf9wcbwa1_W_nj0Xg",
        "title": "Hotel Transylvania 4 - Animation Movies 2022 Full English | Kids Movies | Cartoon Disney",
        "description": "",
        "thumbnails": {
          "default": {
            "url": "https://i.ytimg.com/vi/9qPKlNoGzyg/default.jpg",
            "width": 120,
            "height": 90
          },
          "medium": {
            "url": "https://i.ytimg.com/vi/9qPKlNoGzyg/mqdefault.jpg",
            "width": 320,
            "height": 180
          },
          "high": {
            "url": "https://i.ytimg.com/vi/9qPKlNoGzyg/hqdefault.jpg",
            "width": 480,
            "height": 360
          }
        },
        "channelTitle": "Action_movie123",
        "liveBroadcastContent": "none",
        "publishTime": "2022-06-26T15:53:39Z"
      }
    },
    {
      "kind": "youtube#searchResult",
      "etag": "m5gb2wnrd9CTw-TIbHwf0pmtklA",
      "id": {
        "kind": "youtube#video",
        "videoId": "qqGdCRXEU4s"
      },
      "snippet": {
        "publishedAt": "2020-10-25T01:35:47Z",
        "channelId": "UCZSlI9vDA43rZFp2MfPu0DQ",
        "title": "Ratatouille Full movie from Walt Disney #ratatouille #Waltdisney #Fullmovie #cartoon",
        "description": "ratatouille,download ratatouille,how to download ratatouille,ratatouille movie download,ratatouille full movie,ratatouille full movie ...",
        "thumbnails": {
          "default": {
            "url": "https://i.ytimg.com/vi/qqGdCRXEU4s/default.jpg",
            "width": 120,
            "height": 90
          },
          "medium": {
            "url": "https://i.ytimg.com/vi/qqGdCRXEU4s/mqdefault.jpg",
            "width": 320,
            "height": 180
          },
          "high": {
            "url": "https://i.ytimg.com/vi/qqGdCRXEU4s/hqdefault.jpg",
            "width": 480,
            "height": 360
          }
        },
        "channelTitle": "best Clips",
        "liveBroadcastContent": "none",
        "publishTime": "2020-10-25T01:35:47Z"
      }
    },
    {
      "kind": "youtube#searchResult",
      "etag": "J0zyIBOlFK79EUFzu-PBcs67nEA",
      "id": {
        "kind": "youtube#video",
        "videoId": "u-zeOTbkc0Q"
      },
      "snippet": {
        "publishedAt": "2022-08-01T18:45:01Z",
        "channelId": "UCw7SNYrYei7F5ttQO3o-rpA",
        "title": "Alien Invasion 👽 | Sneak Peek | ZOMBIES 3 | Disney Original Movie | @Disney Channel",
        "description": "Something out of this world is coming to Seabrook! ZOMBIES 3 premieres August 12th on Disney Channel in the U.S.! Watch the ...",
        "thumbnails": {
          "default": {
            "url": "https://i.ytimg.com/vi/u-zeOTbkc0Q/default.jpg",
            "width": 120,
            "height": 90
          },
          "medium": {
            "url": "https://i.ytimg.com/vi/u-zeOTbkc0Q/mqdefault.jpg",
            "width": 320,
            "height": 180
          },
          "high": {
            "url": "https://i.ytimg.com/vi/u-zeOTbkc0Q/hqdefault.jpg",
            "width": 480,
            "height": 360
          }
        },
        "channelTitle": "Disney Channel",
        "liveBroadcastContent": "none",
        "publishTime": "2022-08-01T18:45:01Z"
      }
    },
    {
      "kind": "youtube#searchResult",
      "etag": "BI-S4C_7IkAl46_n8WvfkLs2mq0",
      "id": {
        "kind": "youtube#video",
        "videoId": "_JzumGWr5HI"
      },
      "snippet": {
        "publishedAt": "2021-11-26T20:48:03Z",
        "channelId": "UCV-a7K1GDN533phYqczxmcA",
        "title": "children favorite movie, finding nemo, disney movies free to watch",
        "description": "Finding Nemo Children's favorite movie new hollywood movies in hindi, new hollywood movies 2020 full movie in hindi hd, new ...",
        "thumbnails": {
          "default": {
            "url": "https://i.ytimg.com/vi/_JzumGWr5HI/default.jpg",
            "width": 120,
            "height": 90
          },
          "medium": {
            "url": "https://i.ytimg.com/vi/_JzumGWr5HI/mqdefault.jpg",
            "width": 320,
            "height": 180
          },
          "high": {
            "url": "https://i.ytimg.com/vi/_JzumGWr5HI/hqdefault.jpg",
            "width": 480,
            "height": 360
          }
        },
        "channelTitle": "BK Go",
        "liveBroadcastContent": "none",
        "publishTime": "2021-11-26T20:48:03Z"
      }
    },
    {
      "kind": "youtube#searchResult",
      "etag": "YCn0nnNROvm_wDdgHBORNcU9tIE",
      "id": {
        "kind": "youtube#video",
        "videoId": "28CIeC8cZks"
      },
      "snippet": {
        "publishedAt": "2021-09-25T18:30:03Z",
        "channelId": "UCcXp-kU_oZkKEcyeNdGztTw",
        "title": "Kena: Bridge of Spirits Full Movie [1080p HD 60FPS]",
        "description": "The story of this video game Kena: Bridge of Spirits is fully edited into a movie. And this is my first game movie but I tried my best to ...",
        "thumbnails": {
          "default": {
            "url": "https://i.ytimg.com/vi/28CIeC8cZks/default.jpg",
            "width": 120,
            "height": 90
          },
          "medium": {
            "url": "https://i.ytimg.com/vi/28CIeC8cZks/mqdefault.jpg",
            "width": 320,
            "height": 180
          },
          "high": {
            "url": "https://i.ytimg.com/vi/28CIeC8cZks/hqdefault.jpg",
            "width": 480,
            "height": 360
          }
        },
        "channelTitle": "Psptoys",
        "liveBroadcastContent": "none",
        "publishTime": "2021-09-25T18:30:03Z"
      }
    },
    {
      "kind": "youtube#searchResult",
      "etag": "ntHNzNpz58Uir_zzyqT_yCq6Eh8",
      "id": {
        "kind": "youtube#video",
        "videoId": "f-OL58H7IOE"
      },
      "snippet": {
        "publishedAt": "2020-01-08T02:00:12Z",
        "channelId": "UCX8SxSyafIZZL5GbYzZ42Ag",
        "title": "FROZEN 2 Full Movie in English - Cartoon Disney Movies 2020",
        "description": "FROZEN 2 Full Movie in English - Cartoon Disney Movies 2020 FROZEN 2 Full Movie in English - Cartoon Disney Movies 2020 ...",
        "thumbnails": {
          "default": {
            "url": "https://i.ytimg.com/vi/f-OL58H7IOE/default.jpg",
            "width": 120,
            "height": 90
          },
          "medium": {
            "url": "https://i.ytimg.com/vi/f-OL58H7IOE/mqdefault.jpg",
            "width": 320,
            "height": 180
          },
          "high": {
            "url": "https://i.ytimg.com/vi/f-OL58H7IOE/hqdefault.jpg",
            "width": 480,
            "height": 360
          }
        },
        "channelTitle": "Almira Elysia",
        "liveBroadcastContent": "none",
        "publishTime": "2020-01-08T02:00:12Z"
      }
    },
    {
      "kind": "youtube#searchResult",
      "etag": "r3IWsIAY_4Rb7nu-IkzFF5FxLUM",
      "id": {
        "kind": "youtube#video",
        "videoId": "eu1jekOB7sw"
      },
      "snippet": {
        "publishedAt": "2016-07-25T14:37:34Z",
        "channelId": "UCdanhsZYnPlqEBULn63ovHg",
        "title": "Disney Movies For Kids ☆ Movies For Kids ☆ Animation Movies For Children",
        "description": "Thank u for watching! Please like, comment, subscribe for more than video. Watch More Videos on: https://goo.gl/FEvYoj.",
        "thumbnails": {
          "default": {
            "url": "https://i.ytimg.com/vi/eu1jekOB7sw/default.jpg",
            "width": 120,
            "height": 90
          },
          "medium": {
            "url": "https://i.ytimg.com/vi/eu1jekOB7sw/mqdefault.jpg",
            "width": 320,
            "height": 180
          },
          "high": {
            "url": "https://i.ytimg.com/vi/eu1jekOB7sw/hqdefault.jpg",
            "width": 480,
            "height": 360
          }
        },
        "channelTitle": "Tilton Laura",
        "liveBroadcastContent": "none",
        "publishTime": "2016-07-25T14:37:34Z"
      }
    },
    {
      "kind": "youtube#searchResult",
      "etag": "kM2WLjm38G12Nts-gFZBdW7verc",
      "id": {
        "kind": "youtube#video",
        "videoId": "_b6jm4o8pT4"
      },
      "snippet": {
        "publishedAt": "2022-01-19T06:30:12Z",
        "channelId": "UCFVCPp4UhBs5EW-O72VNusw",
        "title": "Tom Little and The Magic Mirror Full Movie | Animated Family Adventure Movie | Kids Full Movie 2022",
        "description": "Tom Little and The Magic Mirror Full Movie | Animated Family Adventure Movie | Kids Full Movie 2022 In a magical world, small ...",
        "thumbnails": {
          "default": {
            "url": "https://i.ytimg.com/vi/_b6jm4o8pT4/default.jpg",
            "width": 120,
            "height": 90
          },
          "medium": {
            "url": "https://i.ytimg.com/vi/_b6jm4o8pT4/mqdefault.jpg",
            "width": 320,
            "height": 180
          },
          "high": {
            "url": "https://i.ytimg.com/vi/_b6jm4o8pT4/hqdefault.jpg",
            "width": 480,
            "height": 360
          }
        },
        "channelTitle": "MEK Kids",
        "liveBroadcastContent": "none",
        "publishTime": "2022-01-19T06:30:12Z"
      }
    },
    {
      "kind": "youtube#searchResult",
      "etag": "UrXsVLhqMT4lPNbrMmTjWbJS5Gg",
      "id": {
        "kind": "youtube#video",
        "videoId": "5FTfo8SnqtU"
      },
      "snippet": {
        "publishedAt": "2022-02-03T13:24:19Z",
        "channelId": "UC0j8PtFAyC40UK5TeWmNWdw",
        "title": "Dumbo Full Movie in English - Disney Animation Movie",
        "description": "Dumbo, an elephant who has enormous ears, is always ridiculed. A small mouse comes to his rescue and motivates him so that ...",
        "thumbnails": {
          "default": {
            "url": "https://i.ytimg.com/vi/5FTfo8SnqtU/default.jpg",
            "width": 120,
            "height": 90
          },
          "medium": {
            "url": "https://i.ytimg.com/vi/5FTfo8SnqtU/mqdefault.jpg",
            "width": 320,
            "height": 180
          },
          "high": {
            "url": "https://i.ytimg.com/vi/5FTfo8SnqtU/hqdefault.jpg",
            "width": 480,
            "height": 360
          }
        },
        "channelTitle": "Piedra negra",
        "liveBroadcastContent": "none",
        "publishTime": "2022-02-03T13:24:19Z"
      }
    },
    {
      "kind": "youtube#searchResult",
      "etag": "Imm2GVs8t3YT438k89etbggLVJs",
      "id": {
        "kind": "youtube#video",
        "videoId": "a6mia-ckyK4"
      },
      "snippet": {
        "publishedAt": "2020-02-15T19:36:38Z",
        "channelId": "UCacQUXPbYA4jaM4EMGCY5sw",
        "title": "New Animation Movies 2021 Full Movies English   Kids movies  halloween movie coco full movie",
        "description": "Follow me on Instagram - https://www.instagram.com/binara_sadunsha/ Halloween movies for kids halloween cartoon movies ...",
        "thumbnails": {
          "default": {
            "url": "https://i.ytimg.com/vi/a6mia-ckyK4/default.jpg",
            "width": 120,
            "height": 90
          },
          "medium": {
            "url": "https://i.ytimg.com/vi/a6mia-ckyK4/mqdefault.jpg",
            "width": 320,
            "height": 180
          },
          "high": {
            "url": "https://i.ytimg.com/vi/a6mia-ckyK4/hqdefault.jpg",
            "width": 480,
            "height": 360
          }
        },
        "channelTitle": "sIgNinG OuT",
        "liveBroadcastContent": "none",
        "publishTime": "2020-02-15T19:36:38Z"
      }
    },
    {
      "kind": "youtube#searchResult",
      "etag": "xbOOjp9_u9XCC41O0hW6n9kMbXk",
      "id": {
        "kind": "youtube#video",
        "videoId": "Jn9_LGNXWx0"
      },
      "snippet": {
        "publishedAt": "2022-08-01T17:00:21Z",
        "channelId": "UCIQz7nN_zTfIoSOh7HasYIQ",
        "title": "BREAKING: Johnny Releases His Own Jack Sparrow Movie WITHOUT Disney",
        "description": "BREAKING: Johnny Depp Releases His Own Jack Sparrow Short Movie WITHOUT Disney Johnny Depp has released his own ...",
        "thumbnails": {
          "default": {
            "url": "https://i.ytimg.com/vi/Jn9_LGNXWx0/default.jpg",
            "width": 120,
            "height": 90
          },
          "medium": {
            "url": "https://i.ytimg.com/vi/Jn9_LGNXWx0/mqdefault.jpg",
            "width": 320,
            "height": 180
          },
          "high": {
            "url": "https://i.ytimg.com/vi/Jn9_LGNXWx0/hqdefault.jpg",
            "width": 480,
            "height": 360
          }
        },
        "channelTitle": "Just In",
        "liveBroadcastContent": "none",
        "publishTime": "2022-08-01T17:00:21Z"
      }
    },
    {
      "kind": "youtube#searchResult",
      "etag": "cZOzPa7YV6ZNGnW-Og7SPCY7RYM",
      "id": {
        "kind": "youtube#video",
        "videoId": "VOXJMqs0-wU"
      },
      "snippet": {
        "publishedAt": "2022-05-21T17:42:12Z",
        "channelId": "UCSYhnhdf9wcbwa1_W_nj0Xg",
        "title": "The Bad Guys - Animation Movies 2022 Full English | Kids Movies | Cartoon Disney",
        "description": "",
        "thumbnails": {
          "default": {
            "url": "https://i.ytimg.com/vi/VOXJMqs0-wU/default.jpg",
            "width": 120,
            "height": 90
          },
          "medium": {
            "url": "https://i.ytimg.com/vi/VOXJMqs0-wU/mqdefault.jpg",
            "width": 320,
            "height": 180
          },
          "high": {
            "url": "https://i.ytimg.com/vi/VOXJMqs0-wU/hqdefault.jpg",
            "width": 480,
            "height": 360
          }
        },
        "channelTitle": "Action_movie123",
        "liveBroadcastContent": "none",
        "publishTime": "2022-05-21T17:42:12Z"
      }
    },
    {
      "kind": "youtube#searchResult",
      "etag": "lT1bWau-nI_CA7KRCGdchKTBw4I",
      "id": {
        "kind": "youtube#video",
        "videoId": "nsYekr-9bP0"
      },
      "snippet": {
        "publishedAt": "2022-07-30T20:42:52Z",
        "channelId": "UCIvjHBJvS4koTix_Z1S15Aw",
        "title": "Ranking Disney Movies | Andrea &amp; Lewis #shorts",
        "description": "",
        "thumbnails": {
          "default": {
            "url": "https://i.ytimg.com/vi/nsYekr-9bP0/default.jpg",
            "width": 120,
            "height": 90
          },
          "medium": {
            "url": "https://i.ytimg.com/vi/nsYekr-9bP0/mqdefault.jpg",
            "width": 320,
            "height": 180
          },
          "high": {
            "url": "https://i.ytimg.com/vi/nsYekr-9bP0/hqdefault.jpg",
            "width": 480,
            "height": 360
          }
        },
        "channelTitle": "Andrea & Lewis",
        "liveBroadcastContent": "none",
        "publishTime": "2022-07-30T20:42:52Z"
      }
    },
    {
      "kind": "youtube#searchResult",
      "etag": "HBTQTsiEpC9Zf_irxQXxgnrxdWg",
      "id": {
        "kind": "youtube#video",
        "videoId": "777vay9vLvE"
      },
      "snippet": {
        "publishedAt": "2021-05-16T10:27:18Z",
        "channelId": "UCM0U5_jaB7Kio8ehUwKuyYA",
        "title": "Switched Full Movie",
        "description": "",
        "thumbnails": {
          "default": {
            "url": "https://i.ytimg.com/vi/777vay9vLvE/default.jpg",
            "width": 120,
            "height": 90
          },
          "medium": {
            "url": "https://i.ytimg.com/vi/777vay9vLvE/mqdefault.jpg",
            "width": 320,
            "height": 180
          },
          "high": {
            "url": "https://i.ytimg.com/vi/777vay9vLvE/hqdefault.jpg",
            "width": 480,
            "height": 360
          }
        },
        "channelTitle": "Zero Two",
        "liveBroadcastContent": "none",
        "publishTime": "2021-05-16T10:27:18Z"
      }
    },
    {
      "kind": "youtube#searchResult",
      "etag": "FqF8OIBK7jl6qEyRjp8Qn7udJ2g",
      "id": {
        "kind": "youtube#video",
        "videoId": "4hedoGtWSOw"
      },
      "snippet": {
        "publishedAt": "2022-08-02T15:00:05Z",
        "channelId": "UCoK5NOxkZBLfI_5eqf8Es4Q",
        "title": "CHEF ADLEY feeds NAVEY!!  Niko meets the Real Spiderman &amp; Superhero Dinner! Disney Wish Family Movie",
        "description": "Meeting Pirate Goofy and Captain Mickey on our last day!! JOIN OUR FAM!! --- http://goo.gl/rfgp8V Best Last Cruise Day Ever ...",
        "thumbnails": {
          "default": {
            "url": "https://i.ytimg.com/vi/4hedoGtWSOw/default.jpg",
            "width": 120,
            "height": 90
          },
          "medium": {
            "url": "https://i.ytimg.com/vi/4hedoGtWSOw/mqdefault.jpg",
            "width": 320,
            "height": 180
          },
          "high": {
            "url": "https://i.ytimg.com/vi/4hedoGtWSOw/hqdefault.jpg",
            "width": 480,
            "height": 360
          }
        },
        "channelTitle": "Shonduras",
        "liveBroadcastContent": "none",
        "publishTime": "2022-08-02T15:00:05Z"
      }
    },
    {
      "kind": "youtube#searchResult",
      "etag": "cR-jPhP4NlwuKKX2W2HzsfTjhP4",
      "id": {
        "kind": "youtube#video",
        "videoId": "Jfzqyf8FC4s"
      },
      "snippet": {
        "publishedAt": "2021-10-09T01:50:12Z",
        "channelId": "UCH9bCGgYC6s9uCZZLRd3j7Q",
        "title": "Disney&#39;s Encanto full movie English ||Punch Box Studios||",
        "description": "The Madrigals are an extraordinary family who live hidden in the of Colombia in a charmed place camoudanger the Encanto.",
        "thumbnails": {
          "default": {
            "url": "https://i.ytimg.com/vi/Jfzqyf8FC4s/default.jpg",
            "width": 120,
            "height": 90
          },
          "medium": {
            "url": "https://i.ytimg.com/vi/Jfzqyf8FC4s/mqdefault.jpg",
            "width": 320,
            "height": 180
          },
          "high": {
            "url": "https://i.ytimg.com/vi/Jfzqyf8FC4s/hqdefault.jpg",
            "width": 480,
            "height": 360
          }
        },
        "channelTitle": "PUNCH BOX STUDIOS",
        "liveBroadcastContent": "none",
        "publishTime": "2021-10-09T01:50:12Z"
      }
    }
  ]
}
